redrcp/__about__.py
redrcp/__init__.py
redrcp/rcp/__init__.py
redrcp/rcp/enums.py
redrcp/rcp/error_messages.py
redrcp/rcp/message_arguments.py
redrcp/rcp/message_helper.py
redrcp/rcp/rcp_commands.py
redrcp/rcp/rcp_rx_handler.py
redrcp/transport/__init__.py
redrcp/transport/serial.py
redrcp-1.2.0.dist-info/METADATA
redrcp-1.2.0.dist-info/WHEEL
redrcp-1.2.0.dist-info/licenses/LICENSE.txt
redrcp-1.2.0.dist-info/RECORD
